dpapi_ng/__init__.py
dpapi_ng/_asn1.py
dpapi_ng/_blob.py
dpapi_ng/_client.py
dpapi_ng/_crypto.py
dpapi_ng/_dns.py
dpapi_ng/_epm.py
dpapi_ng/_gkdi.py
dpapi_ng/_pkcs7.py
dpapi_ng/_security_descriptor.py
dpapi_ng/_version.py
dpapi_ng/_rpc/__init__.py
dpapi_ng/_rpc/_auth.py
dpapi_ng/_rpc/_bind.py
dpapi_ng/_rpc/_client.py
dpapi_ng/_rpc/_pdu.py
dpapi_ng/_rpc/_request.py
dpapi_ng/_rpc/_verification.py
dpapi_ng-0.2.0.dist-info/LICENSE
dpapi_ng-0.2.0.dist-info/METADATA
dpapi_ng-0.2.0.dist-info/WHEEL
dpapi_ng-0.2.0.dist-info/top_level.txt
dpapi_ng-0.2.0.dist-info/RECORD
