Metadata-Version: 2.1
Name: dpapi-ng
Version: 0.2.0
Summary: DPAPI NG decryption for Python
Author-email: Jordan Borean <jborean93@gmail.com>
License: MIT License
Project-URL: homepage, https://github.com/jborean93/dpapi-ng
Keywords: dpapi,dpapi-ng,laps
Classifier: Development Status :: 4 - Beta
Classifier: License :: OSI Approved :: MIT License
Classifier: Programming Language :: Python :: 3
Classifier: Programming Language :: Python :: 3.7
Classifier: Programming Language :: Python :: 3.8
Classifier: Programming Language :: Python :: 3.9
Classifier: Programming Language :: Python :: 3.10
Classifier: Programming Language :: Python :: 3.11
Requires-Python: >=3.7
License-File: LICENSE
Requires-Dist: dnspython (>=2.0.0)
Requires-Dist: cryptography
Requires-Dist: pyspnego (>=0.9.0)
Provides-Extra: kerberos
Requires-Dist: pyspnego[kerberos] (>=0.9.0) ; extra == 'kerberos'
